skfe/__init__.py
scikit_fe-0.1.0.dist-info/LICENSE
scikit_fe-0.1.0.dist-info/METADATA
scikit_fe-0.1.0.dist-info/WHEEL
scikit_fe-0.1.0.dist-info/top_level.txt
scikit_fe-0.1.0.dist-info/RECORD
