Metadata-Version: 2.1
Name: scikit-fe
Version: 0.1.0
Summary: Feature Engineering Based On Scikit-learn
Home-page: https://github.com/aitrek/scikit-fe
Author: zhaojianqiang
Author-email: zhaojianqiang@foxmail.com
License: UNKNOWN
Platform: UNKNOWN
